{
  "gitSyncId": "66b0cb913770616d0d7f7228_3aed6c74-ec5d-47bf-a831-786d9622358e",
  "id": "Page1 Copy_JSObject1.myFun2",
  "pluginId": "js-plugin",
  "pluginType": "JS",
  "unpublishedAction": {
    "actionConfiguration": {
      "encodeParamsToggle": true,
      "jsArguments": [],
      "paginationType": "NONE",
      "timeoutInMillisecond": 10000
    },
    "clientSideExecution": true,
    "collectionId": "Page1 Copy_JSObject1",
    "confirmBeforeExecute": false,
    "datasource": {
      "isAutoGenerated": false,
      "name": "UNUSED_DATASOURCE",
      "pluginId": "js-plugin"
    },
    "dynamicBindingPathList": [
      {
        "key": "body"
      }
    ],
    "executeOnLoad": false,
    "fullyQualifiedName": "JSObject1.myFun2",
    "name": "myFun2",
    "pageId": "Page1 Copy",
    "userSetOnLoad": false
  }
}